dictum_backend_mariadb/__init__.py
dictum_backend_mariadb/mariadb.py
dictum_backend_mariadb-0.1.0.dist-info/LICENSE
dictum_backend_mariadb-0.1.0.dist-info/METADATA
dictum_backend_mariadb-0.1.0.dist-info/WHEEL
dictum_backend_mariadb-0.1.0.dist-info/entry_points.txt
dictum_backend_mariadb-0.1.0.dist-info/RECORD
