Metadata-Version: 2.1
Name: dictum-backend-mariadb
Version: 0.1.0
Summary: MariaDB backend for Dictum
Author: Mikhail Akimov
Requires-Python: >=3.9,<3.13
Classifier: Programming Language :: Python :: 3
Classifier: Programming Language :: Python :: 3.9
Classifier: Programming Language :: Python :: 3.10
Classifier: Programming Language :: Python :: 3.11
Classifier: Programming Language :: Python :: 3.12
Requires-Dist: dictum-core (>=0.1,<0.2)
Requires-Dist: pymysql (>=1.1.0,<2.0.0)
